torchdensityestimation/__init__.py
torchdensityestimation/difference/__init__.py
torchdensityestimation/difference/lsdd.py
torchdensityestimation/ratio/__init__.py
torchdensityestimation/ratio/rulsif.py
torchdensityestimation-1.0.0.dist-info/licenses/LICENSE
torchdensityestimation-1.0.0.dist-info/METADATA
torchdensityestimation-1.0.0.dist-info/WHEEL
torchdensityestimation-1.0.0.dist-info/top_level.txt
torchdensityestimation-1.0.0.dist-info/RECORD
